kombai/__init__.py
kombai-0.0.1a0.dist-info/LICENSE
kombai-0.0.1a0.dist-info/WHEEL
kombai-0.0.1a0.dist-info/METADATA
kombai-0.0.1a0.dist-info/RECORD
