Metadata-Version: 2.1
Name: kombai
Version: 0.0.1a0
Summary: Terminal based structured data viewer and editor written in Python
License: MIT
Author: kracekumar
Author-email: me@kracekumar.com
Requires-Python: >=3.7,<4.0
Classifier: License :: OSI Approved :: MIT License
Classifier: Programming Language :: Python :: 3
Classifier: Programming Language :: Python :: 3.7
Classifier: Programming Language :: Python :: 3.8
Classifier: Programming Language :: Python :: 3.9
Requires-Dist: SQLAlchemy (>=1.4,<1.4.23)
Requires-Dist: importlib-metadata (>=4.8.1,<5.0.0); python_version < "3.8"
Requires-Dist: pytest-cov (>=2.12.1,<3.0.0)
Requires-Dist: textual (>=0.1.10,<0.2.0)
